VaniLite/__init__.py
VaniLite/errors.py
VaniLite/utils.py
VaniLite/vani.py
VaniLite-0.0.2.dist-info/LICENSE
VaniLite-0.0.2.dist-info/METADATA
VaniLite-0.0.2.dist-info/WHEEL
VaniLite-0.0.2.dist-info/top_level.txt
VaniLite-0.0.2.dist-info/RECORD
