Metadata-Version: 2.1
Name: VaniLite
Version: 0.0.2
Summary: Multi-Language Support Library for Python Projects
Home-page: https://github.com/TelegramExtended/VaniLite
Author: WarnerStark
Author-email: starktechfriday@gmail.com
Keywords: multi-language,localization,i18n,python,VaniLite,VaniLite-lite
Classifier: Development Status :: 3 - Alpha
Classifier: Intended Audience :: Developers
Classifier: License :: OSI Approved :: GNU General Public License v3 (GPLv3)
Classifier: Programming Language :: Python :: 3.8
Classifier: Programming Language :: Python :: 3.9
License-File: LICENSE
